iotPervasiveServiceSDKMicroPyhon/__init__.py
iotPervasiveServiceSDKMicroPyhon/config.py
iotPervasiveServiceSDKMicroPyhon/proxySDK.py
iotPervasiveServiceSDKMicroPyhon-0.0.1.dist-info/LICENSE
iotPervasiveServiceSDKMicroPyhon-0.0.1.dist-info/METADATA
iotPervasiveServiceSDKMicroPyhon-0.0.1.dist-info/WHEEL
iotPervasiveServiceSDKMicroPyhon-0.0.1.dist-info/top_level.txt
iotPervasiveServiceSDKMicroPyhon-0.0.1.dist-info/RECORD
